Workbook
Name aporte: Planilha1!$C$16
Name patrimonio: Planilha1!$C$19
Name qtd_anos: Planilha1!$C$17
Name Rendimento_Carteira: Planilha1!$C$12
Name salario: Planilha1!$C$11
Name sugestao_investimento: Planilha1!$C$13
Name taxa_mensal: Planilha1!$C$18

Sheet Planilha1
B10: CONFIGURAÇÕES
B11: Salário | C11: 4200
B12: Rendimento Carteira | C12: 0.0085
B13: Sugestão de Investimento (30%) | C13: =$C$11*30% -> 1260
B15: INVESTIMENTO MENSAL
B16: Quanto investir por mês ? | C16: 1260
B17: Por quantos anos ? | C17: 5
B18: Taxa de rendimento mensal ? | C18: 0.01079
B19: Quanto de patrimônio acumulado terei ? | C19: =FV(taxa_mensal,qtd_anos*12,aporte*-1) -> 105558.91
B20: Dividendos mensais ? | C20: =patrimonio*Rendimento_Carteira -> 897.25075
B22: CENÁRIOS | D22: DIVIDENDOS
B23: Quanto em 2 anos? | C23: =FV($C$18,2*12,$C$16)*-1 -> 34306.81 | D23: =C23*Rendimento_Carteira -> 291.60789
B24: Quanto em 5 anos? | C24: =FV($C$18,5*12,$C$16)*-1 -> 105558.91 | D24: =C24*Rendimento_Carteira -> 897.25075
B25: Quanto em 10 anos? | C25: =FV($C$18,10*12,$C$16)*-1 -> 306538.11 | D25: =C25*Rendimento_Carteira -> 2605.5739
B26: Quanto em 20 anos? | C26: =FV($C$18,20*12,$C$16)*-1 -> 1417750 | D26: =C26*Rendimento_Carteira -> 12050.875
B27: Quanto em 30 anos? | C27: =FV($C$18,30*12,$C$16)*-1 -> 5445933.8 | D27: =C27*Rendimento_Carteira -> 46290.437
B28: Quanto em 50 anos? | C28: =FV($C$18,50*12,$C$16)*-1 -> 72982171 | D28: =C28*Rendimento_Carteira -> 620348.45
B30: PERFIL | C30: AGRESSIVO
B31: VALOR A SER INVESTIDO POR MÊS | C31: =aporte -> 1260
B33: TIPO DE FII | C33: Percentual Sugerido | D33: Valores
B34: PAPEL | C34: =VLOOKUP($C$30&"-"&B34,Planilha2!D7:G25,4,FALSE) -> 0.5 | D34: =C34*$C$31 -> 630
B35: TIJOLO | C35: =VLOOKUP($C$30&"-"&B35,Planilha2!D8:G26,4,FALSE) -> 0.1 | D35: =C35*$C$31 -> 126
B36: HÍBRIDOS | C36: =VLOOKUP($C$30&"-"&B36,Planilha2!D9:G27,4,FALSE) -> 0.05 | D36: =C36*$C$31 -> 63
B37: FOFs | C37: =VLOOKUP($C$30&"-"&B37,Planilha2!D10:G28,4,FALSE) -> 0.05 | D37: =C37*$C$31 -> 63
B38: DESENVOLVIMENTO | C38: =VLOOKUP($C$30&"-"&B38,Planilha2!D11:G29,4,FALSE) -> 0.2 | D38: =C38*$C$31 -> 252
B39: HOTELARIAS | C39: =VLOOKUP($C$30&"-"&B39,Planilha2!D12:G30,4,FALSE) -> 0.1 | D39: =C39*$C$31 -> 126
C40: =SUM(C34:C39) -> 1 | D40: =SUM(D34:D39) -> 1260

Sheet Planilha2
A1: Quanto investir por mês
A2: Por quantos anos
A3: Taxa de rendimento mensal
A4: Quanto de patrimônio acumulado terei
A5: Dividendos mensais
K6: TESTE DO PROCV
D7: CHAVE | E7: PERFIL | F7: TIPO DE FII | G7: % | L7: %
D8: =E8&"-"&F8 -> CONSERVADOR-PAPEL | E8: CONSERVADOR | F8: PAPEL | G8: 0.3 | K8: MODERADO-TIJOLO | L8: =VLOOKUP(K8,$D:$G,4,FALSE) -> 0.35
D9: =E9&"-"&F9 -> CONSERVADOR-TIJOLO | E9: CONSERVADOR | F9: TIJOLO | G9: 0.5
D10: =E10&"-"&F10 -> CONSERVADOR-HÍBRIDOS | E10: CONSERVADOR | F10: HÍBRIDOS | G10: 0.1
D11: =E11&"-"&F11 -> CONSERVADOR-FOFs | E11: CONSERVADOR | F11: FOFs | G11: 0.1
D12: =E12&"-"&F12 -> CONSERVADOR-DESENVOLVIMENTO | E12: CONSERVADOR | F12: DESENVOLVIMENTO | G12: 0
D13: =E13&"-"&F13 -> CONSERVADOR-HOTELARIAS | E13: CONSERVADOR | F13: HOTELARIAS | G13: 0
D14: =E14&"-"&F14 -> MODERADO-PAPEL | E14: MODERADO | F14: PAPEL | G14: 0.32
D15: =E15&"-"&F15 -> MODERADO-TIJOLO | E15: MODERADO | F15: TIJOLO | G15: 0.35
D16: =E16&"-"&F16 -> MODERADO-HÍBRIDOS | E16: MODERADO | F16: HÍBRIDOS | G16: 0.08
D17: =E17&"-"&F17 -> MODERADO-FOFs | E17: MODERADO | F17: FOFs | G17: 0.05
D18: =E18&"-"&F18 -> MODERADO-DESENVOLVIMENTO | E18: MODERADO | F18: DESENVOLVIMENTO | G18: 0.1
D19: =E19&"-"&F19 -> MODERADO-HOTELARIAS | E19: MODERADO | F19: HOTELARIAS | G19: 0.1
D20: =E20&"-"&F20 -> AGRESSIVO-PAPEL | E20: AGRESSIVO | F20: PAPEL | G20: 0.5
... D25: =E25&"-"&F25 -> AGRESSIVO-HOTELARIAS | E25: AGRESSIVO | F25: HOTELARIAS | G25: 0.1
